dxtils/utils.py
dxtils-0.0.6.dist-info/METADATA
dxtils-0.0.6.dist-info/WHEEL
dxtils-0.0.6.dist-info/top_level.txt
dxtils-0.0.6.dist-info/RECORD
