Metadata-Version: 2.1
Name: dxtils
Version: 0.0.6
Summary: Utilities...
Requires-Python: >=3.10
